Verilog_Assgn_4_Grp_9/booth.v
`timescale 1ps/1ps

// Command to run in Icarus verilog 
// 1. % iverilog -o booth booth_module.v
// 2. % vvp booth
// 3. % gtkwave booth.vcd &

module adder(r1, r2, out);
    input [7:0] r1, r2;
    output [7:0] out;

    // always @(*)
    // begin
    //     $display($time, " Adder Called with A = %b, M = %b",r1,r2);
    // end

    assign out = r1+r2;
endmodule

module shifter(r, out);
    input [15:0] r;
    output [15:0] out;

    // always @(*)
    // begin
    //     $display($time, " SHifter Called with AQ = %b",r);
    // end

    assign out = r>>1;
endmodule

module booth(r1, r2, clk, out);
    input [7:0] r1, r2;
    input clk;

    integer i = 0;
    reg [7:0] r12s;
    always @(r1 or r2)
    begin
        r12s = ~r1 + 8'b00000001;
    end

    output reg [15:0] out;
    always @(r1 or r2)
    begin
        out = r2;
    end

    reg msb, lsb, Q_1;

    always @(r1 or r2)
    begin
        i = 0;
        msb = 0;
        lsb = out[0];
        Q_1 = 0;
    end

    parameter zo = 1, oz = 2, shift = 0, shiftt = 3, acc = 4;
    reg [2:0] state;

    always @(r1 or r2)
    begin
        state[2] = 0;
        state[1] = lsb;
        state[0] = Q_1;
    end

    reg [7:0] a1, a2;
    wire [7:0] aout;
    reg [15:0] s;
    wire [15:0] sout;

    adder doo (a1, a2, aout);

    shifter shiftr (s, sout);

    always @(posedge clk or r1 or r2)
    begin
        case (state)
            zo: 
            begin
                a1<=out[15:8];
                a2<=r1;

                #1 out[15:8] = aout;

                #1 msb = out[15];

                state<=shift;
            end
            oz:
            begin
                a1<=out[15:8];
                a2<=r12s;

                #1 out[15:8] = aout;

                #1 msb = out[15];

                state<=shift;
            end
            shift: 
                begin
                    msb <= out[15];
                    lsb <= out[0];

                    Q_1 = lsb;

                    s<=out;

                    #1 out = sout;

                    lsb = out[0];
                    out[15] = msb;
                    
                    state[1] <= lsb;
                    state[0] <= Q_1;

                    i = i+1;
                end
            shiftt:
                begin
                    msb = out[15];
                    lsb = out[0];

                    Q_1 = lsb;

                    s<=out;

                    #1 out = sout;

                    lsb = out[0];
                    out[15] = msb;
                    
                    state[1] <= lsb;
                    state[0] <= Q_1;

                    i=i+1;
                end
            acc:
                state <= acc;
        endcase     

        if(i>=8) 
        begin
            state <= 4;
        end

        // #1 $display($time, "out = %b, state = %b", out, state);
    end
endmodule

// Test Bench to test our code ... (Please follow commented lines for what to do at each required step IN or MOVE)
module test_bench;
    reg [7:0] r1, r2;
    reg clock;

    wire [15:0] out;

    booth test (r1, r2, clock, out);

    initial
        begin
            clock = 1;
        end

    initial
        begin
            // To siulate in GTK Wave use command '% gtkwave gcd.vcd &'
            // $dumpfile("booth.vcd");
            // $dumpvars(0,test);

            $monitor($time, "   : r1 = %b, r2 = %b, r1 x r2 = %b", r1, r2, out);

            r1 = 8'b00000101; r2 = 8'b00010100;
            #50 r1 = 3; r2 = 10;
            #50 r1 = -50; r2 = 5;
            #50 $finish;
        end
        always #1 clock = ~clock;
endmodule

Verilog_Assgn_4_Grp_9/booth.vcd
$date
	Wed Aug 30 17:22:09 2023
$end
$version
	Icarus Verilog
$end
$timescale
	1ps
$end
$scope module test_bench $end
$scope module test $end
$var wire 1 ! clk $end
$var wire 8 " r1 [7:0] $end
$var wire 8 # r2 [7:0] $end
$var wire 16 $ sout [15:0] $end
$var wire 8 % aout [7:0] $end
$var parameter 32 & acc $end
$var parameter 32 ' oz $end
$var parameter 32 ( shift $end
$var parameter 32 ) shiftt $end
$var parameter 32 * zo $end
$var reg 1 + Q_1 $end
$var reg 8 , a1 [7:0] $end
$var reg 8 - a2 [7:0] $end
$var reg 1 . lsb $end
$var reg 1 / msb $end
$var reg 16 0 out [15:0] $end
$var reg 8 1 r12s [7:0] $end
$var reg 16 2 s [15:0] $end
$var reg 3 3 state [2:0] $end
$var integer 32 4 i [31:0] $end
$scope module doo $end
$var wire 8 5 r1 [7:0] $end
$var wire 8 6 r2 [7:0] $end
$var wire 8 7 out [7:0] $end
$upscope $end
$scope module shiftr $end
$var wire 16 8 r [15:0] $end
$var wire 16 9 out [15:0] $end
$upscope $end
$upscope $end
$upscope $end
$enddefinitions $end
$comment Show the parameter values. $end
$dumpall
b1 *
b11 )
b0 (
b10 '
b100 &
$end
#0
$dumpvars
b0xxxxxxxxxxxxxxx 9
bx 8
bx 7
bx 6
bx 5
b0 4
b0 3
bx 2
b11111011 1
b10100 0
0/
0.
bx -
bx ,
0+
bx %
b0xxxxxxxxxxxxxxx $
b10100 #
b101 "
1!
$end
#1
0!
#2
b1010 $
b1010 9
b10100 2
b10100 8
1!
#3
b1 4
b1010 0
0!
#4
b101 $
b101 9
b1010 2
b1010 8
1!
#5
b10 3
b10 4
1.
b101 0
0!
#6
b11111011 %
b11111011 7
b11111011 -
b11111011 6
b0 ,
b0 5
1!
#7
b1111101100000101 0
0!
#8
b0 3
1/
1!
#9
0!
#10
b111110110000010 $
b111110110000010 9
b1111101100000101 2
b1111101100000101 8
1+
1!
#11
b1 3
b11 4
0.
b1111110110000010 0
0!
#12
b101 -
b101 6
b10 %
b10 7
b11111101 ,
b11111101 5
1!
#13
b1010000010 0
0!
#14
b0 3
0/
1!
#15
0!
#16
b101000001 $
b101000001 9
b1010000010 2
b1010000010 8
0+
1!
#17
b10 3
b100 4
1.
b101000001 0
0!
#18
b11111011 -
b11111011 6
b11111100 %
b11111100 7
b1 ,
b1 5
1!
#19
b1111110001000001 0
0!
#20
b0 3
1/
1!
#21
0!
#22
b111111000100000 $
b111111000100000 9
b1111110001000001 2
b1111110001000001 8
1+
1!
#23
b1 3
b101 4
0.
b1111111000100000 0
0!
#24
b101 -
b101 6
b11 %
b11 7
b11111110 ,
b11111110 5
1!
#25
b1100100000 0
0!
#26
b0 3
0/
1!
#27
0!
#28
b110010000 $
b110010000 9
b1100100000 2
b1100100000 8
0+
1!
#29
b110 4
b110010000 0
0!
#30
b11001000 $
b11001000 9
b110010000 2
b110010000 8
1!
#31
b111 4
b11001000 0
0!
#32
b1100100 $
b1100100 9
b11001000 2
b11001000 8
1!
#33
b100 3
b1000 4
b1100100 0
0!
#34
1!
#35
0!
#36
1!
#37
0!
#38
1!
#39
0!
#40
1!
#41
0!
#42
1!
#43
0!
#44
1!
#45
0!
#46
1!
#47
0!
#48
1!
#49
0!
#50
b101 $
b101 9
b1010 2
b1010 8
b11111101 1
b1010 0
b0 4
b0 3
1!
b1010 #
b11 "
#51
b10 3
b1 4
1.
b101 0
0!
#52
b11111101 -
b11111101 6
b11111101 %
b11111101 7
b0 ,
b0 5
1!
#53
b1111110100000101 0
0!
#54
b0 3
1/
1!
#55
0!
#56
b111111010000010 $
b111111010000010 9
b1111110100000101 2
b1111110100000101 8
1+
1!
#57
b1 3
b10 4
0.
b1111111010000010 0
0!
#58
b11 -
b11 6
b1 %
b1 7
b11111110 ,
b11111110 5
1!
#59
b110000010 0
0!
#60
b0 3
0/
1!
#61
0!
#62
b11000001 $
b11000001 9
b110000010 2
b110000010 8
0+
1!
#63
b10 3
b11 4
1.
b11000001 0
0!
#64
b11111101 -
b11111101 6
b11111101 %
b11111101 7
b0 ,
b0 5
1!
#65
b1111110111000001 0
0!
#66
b0 3
1/
1!
#67
0!
#68
b111111011100000 $
b111111011100000 9
b1111110111000001 2
b1111110111000001 8
1+
1!
#69
b1 3
b100 4
0.
b1111111011100000 0
0!
#70
b11 -
b11 6
b1 %
b1 7
b11111110 ,
b11111110 5
1!
#71
b111100000 0
0!
#72
b0 3
0/
1!
#73
0!
#74
b11110000 $
b11110000 9
b111100000 2
b111100000 8
0+
1!
#75
b101 4
b11110000 0
0!
#76
b1111000 $
b1111000 9
b11110000 2
b11110000 8
1!
#77
b110 4
b1111000 0
0!
#78
b111100 $
b111100 9
b1111000 2
b1111000 8
1!
#79
b111 4
b111100 0
0!
#80
b11110 $
b11110 9
b111100 2
b111100 8
1!
#81
b100 3
b1000 4
b11110 0
0!
#82
1!
#83
0!
#84
1!
#85
0!
#86
1!
#87
0!
#88
1!
#89
0!
#90
1!
#91
0!
#92
1!
#93
0!
#94
1!
#95
0!
#96
1!
#97
0!
#98
1!
#99
0!
#100
b110010 -
b110010 6
b110010 %
b110010 7
b0 ,
b0 5
b10 3
1.
b0 4
b101 0
b110010 1
1!
b101 #
b11001110 "
#101
b11001000000101 0
0!
#102
b0 3
1!
#103
0!
#104
b1100100000010 $
b1100100000010 9
b11001000000101 2
b11001000000101 8
1+
1!
#105
b1 3
b1 4
0.
b1100100000010 0
0!
#106
b11001110 -
b11001110 6
b11100111 %
b11100111 7
b11001 ,
b11001 5
1!
#107
b1110011100000010 0
0!
#108
b0 3
1/
1!
#109
0!
#110
b111001110000001 $
b111001110000001 9
b1110011100000010 2
b1110011100000010 8
0+
1!
#111
b10 3
b10 4
1.
b1111001110000001 0
0!
#112
b110010 -
b110010 6
b100101 %
b100101 7
b11110011 ,
b11110011 5
1!
#113
b10010110000001 0
0!
#114
b0 3
0/
1!
#115
0!
#116
b1001011000000 $
b1001011000000 9
b10010110000001 2
b10010110000001 8
1+
1!
#117
b1 3
b11 4
0.
b1001011000000 0
0!
#118
b11001110 -
b11001110 6
b11100000 %
b11100000 7
b10010 ,
b10010 5
1!
#119
b1110000011000000 0
0!
#120
b0 3
1/
1!
#121
0!
#122
b111000001100000 $
b111000001100000 9
b1110000011000000 2
b1110000011000000 8
0+
1!
#123
b100 4
b1111000001100000 0
0!
#124
b111100000110000 $
b111100000110000 9
b1111000001100000 2
b1111000001100000 8
1!
#125
b101 4
b1111100000110000 0
0!
#126
b111110000011000 $
b111110000011000 9
b1111100000110000 2
b1111100000110000 8
1!
#127
b110 4
b1111110000011000 0
0!
#128
b111111000001100 $
b111111000001100 9
b1111110000011000 2
b1111110000011000 8
1!
#129
b111 4
b1111111000001100 0
0!
#130
b111111100000110 $
b111111100000110 9
b1111111000001100 2
b1111111000001100 8
1!
#131
b100 3
b1000 4
b1111111100000110 0
0!
