Verilog_Assgn_2_Grp_9/Q1_Grp_9/reg_module.v
`timescale 1ps/1ps

// Command to run in Icarus verilog 
// 1. % iverilog -o reg reg_module.v
// 2. % vvp reg
// 3. % gtkwave reg.vcd &

// A module to store 8 16-bit registers and execute LOAD and OUTPUT
module reg8(code,data,op,enable,clock,out);
    input [15:0] data;
    input [2:0] code;
    input [1:0] op;
    input enable,clock;

    always @(posedge clock)
        begin
        // $display($time," code = %d, data = %d, op = %d, enable = %d, out = %d",code,data,op,enable, out);
        $display("\n",$time," R0 = %d, R1 = %d, R2 = %d, R3 = %d, R4 = %d, R5 = %d, R6 = %d, R7 = %d\n",R0,R1,R2,R3,R4,R5,R6,R7);
        end

    output reg [15:0] out;
    reg [15:0] R0,R1,R2,R3,R4,R5,R6,R7;
    
    always @(posedge clock) begin
        if(op==0)
        begin
        case(code)
            3'b000: R0 <= data;
            3'b001: R1 <= data;
            3'b010: R2 <= data;
            3'b011: R3 <= data;
            3'b100: R4 <= data;
            3'b101: R5 <= data;
            3'b110: R6 <= data;
            3'b111: R7 <= data;
        endcase
        end
        #10
        if(enable)
        begin
        case(code)
            3'b000: out <= R0;
            3'b001: out <= R1;
            3'b010: out <= R2;
            3'b011: out <= R3;
            3'b100: out <= R4;
            3'b101: out <= R5;
            3'b110: out <= R6;
            3'b111: out <= R7;
        endcase
        end
        else out <= 16'bz;
    end
endmodule

// A Top-level Module to perform IN and MOVE Operations on Registers
module top_level_module(src, dst, op, enable, data, clock, out);
    input [2:0] src,dst;
    input enable,clock;
    input [15:0] data;
    input [1:0] op;

    // always @(src or dst or op or enable or data)
    //     $display ($time, " Top: src = %d, dst = %d, op = %d, enable = %d, data = %d",src,dst,op,enable,data);

    output [15:0] out;

    reg [15:0] tmp;
    reg [2:0] pcode;
    reg [15:0] pdata;
    reg [1:0] pop;
    reg penable,pclock;

    reg8 oper (pcode, pdata, pop, penable, pclock, out);
    
    always @(posedge clock or enable or data or src or dst or op) begin
        case(op)
            0: 
                begin
                pcode <= dst; 
                pdata <= data;
                pop <= 0;
                penable <= enable;
                pclock <= clock;
                end
            1:
              begin
                pcode <= src; 
                pdata <= data;
                pop <= 1;
                penable <= enable;
                pclock <= clock;

                tmp = out;
              end
            2:
              begin
                pcode <= dst; 
                pdata <= tmp;
                pop <= 0;
                penable <= enable;
                pclock <= clock;
              end
        endcase
    end
endmodule

// Test Bench to test our code ... (Please follow commented lines for what to do at each required step IN or MOVE)
module test_bench;
    reg [2:0] src, dst;
    reg [1:0] op;
    reg enable = 0,clock = 0;
    reg[15:0] data;
    wire [15:0] out;

    top_level_module test (src, dst, op, enable, data, clock, out);

    initial
        begin
            // To siulate in GTK Wave use command '% gtkwave gcd.vcd &'
            // $dumpfile("reg.vcd");
            // $dumpvars(0,test);

            $monitor($time, "   : src = %d, dst = %d, data = %d, op = %d, enable = %d, output = %d", src, dst, data, op, enable, out);
            
            // For each IN Operation : mention the destination and data along with operation = 0
            #100 dst = 3'b000; op = 2'b00; data = 77;

            // To toggle OUTPUT change enable
            #100 enable = 1;

            // For each IN Operation : mention the destination and data along with operation = 0
            #100 dst = 3'b111; op = 2'b00; data = 45;
            #100 dst = 3'b100; op = 2'b00; data = 30;

            // For each MOVE Operation : mention the source and the destination along with operation = 1 followed by a operation = 2
            #100 src = 3'b111; dst = 3'b010; op = 2'b01;
            #100 op = 2'b10;
            // Above change is made to restore a state value
            
            // To toggle OUTPUT change enable
            #100 enable = 0;
            #100 $finish;
        end
        always #10 clock = ~clock;
endmodule

Verilog_Assgn_2_Grp_9/Q1_Grp_9/reg.vcd
$date
	Thu Aug 24 23:44:25 2023
$end
$version
	Icarus Verilog
$end
$timescale
	1ps
$end
$scope module test_bench $end
$scope module test $end
$var wire 1 ! clock $end
$var wire 16 " data [15:0] $end
$var wire 3 # dst [2:0] $end
$var wire 1 $ enable $end
$var wire 2 % op [1:0] $end
$var wire 3 & src [2:0] $end
$var wire 16 ' out [15:0] $end
$var reg 1 ( pclock $end
$var reg 3 ) pcode [2:0] $end
$var reg 16 * pdata [15:0] $end
$var reg 1 + penable $end
$var reg 2 , pop [1:0] $end
$var reg 16 - tmp [15:0] $end
$scope module oper $end
$var wire 1 ( clock $end
$var wire 3 . code [2:0] $end
$var wire 16 / data [15:0] $end
$var wire 1 + enable $end
$var wire 2 0 op [1:0] $end
$var reg 16 1 R0 [15:0] $end
$var reg 16 2 R1 [15:0] $end
$var reg 16 3 R2 [15:0] $end
$var reg 16 4 R3 [15:0] $end
$var reg 16 5 R4 [15:0] $end
$var reg 16 6 R5 [15:0] $end
$var reg 16 7 R6 [15:0] $end
$var reg 16 8 R7 [15:0] $end
$var reg 16 9 out [15:0] $end
$upscope $end
$upscope $end
$upscope $end
$enddefinitions $end
$comment Show the parameter values. $end
$dumpall
$end
#0
$dumpvars
bx 9
bx 8
bx 7
bx 6
bx 5
bx 4
bx 3
bx 2
bx 1
bx 0
bx /
bx .
bx -
bx ,
x+
bx *
bx )
x(
bx '
bx &
bx %
0$
bx #
bx "
0!
$end
#10
1!
#20
0!
#30
1!
#40
0!
#50
1!
#60
0!
#70
1!
#80
0!
#90
1!
#100
0(
0+
b0 ,
b0 0
b1001101 *
b1001101 /
b0 )
b0 .
0!
b1001101 "
b0 %
b0 #
#110
b1001101 1
1(
1!
#120
bz '
bz 9
0!
#130
1!
#140
0!
#150
1!
#160
0!
#170
1!
#180
0!
#190
1!
#200
0(
1+
0!
1$
#210
1(
1!
#220
b1001101 '
b1001101 9
0!
#230
1!
#240
0!
#250
1!
#260
0!
#270
1!
#280
0!
#290
1!
#300
0(
b101101 *
b101101 /
b111 )
b111 .
0!
b101101 "
b111 #
#310
b101101 8
1(
1!
#320
b101101 '
b101101 9
0!
#330
1!
#340
0!
#350
1!
#360
0!
#370
1!
#380
0!
#390
1!
#400
0(
b11110 *
b11110 /
b100 )
b100 .
0!
b11110 "
b100 #
#410
b11110 5
1(
1!
#420
b11110 '
b11110 9
0!
#430
1!
#440
0!
#450
1!
#460
0!
#470
1!
#480
0!
#490
1!
#500
0(
b1 ,
b1 0
b111 )
b111 .
b11110 -
0!
b1 %
b10 #
b111 &
#510
1(
1!
#520
b101101 '
b101101 9
0!
#530
b101101 -
1!
#540
0!
#550
1!
#560
0!
#570
1!
#580
0!
#590
1!
#600
0(
b0 ,
b0 0
b101101 *
b101101 /
b10 )
b10 .
0!
b10 %
#610
b101101 3
1(
1!
#620
0!
#630
1!
#640
0!
#650
1!
#660
0!
#670
1!
#680
0!
#690
1!
#700
0(
0+
0!
0$
#710
1(
1!
#720
bz '
bz 9
0!
